gnuplot_style/__init__.py
gnuplot_style/api.py
gnuplot_style/constants.py
gnuplot_style/core.py
gnuplot_style/gnuplot.mplstyle
gnuplot_style-0.1.2.dist-info/METADATA
gnuplot_style-0.1.2.dist-info/WHEEL
gnuplot_style-0.1.2.dist-info/top_level.txt
gnuplot_style-0.1.2.dist-info/RECORD
