Metadata-Version: 2.4
Name: gnuplot-style
Version: 0.1.2
Summary: Gnuplot-style aesthetics for matplotlib
Author-email: Chi Zhao <dandanv5@hotmail.com>
License: MIT
Project-URL: Homepage, https://github.com/vectorsss/gnuplot-style
Project-URL: Documentation, https://github.com/vectorsss/gnuplot-style#readme
Project-URL: Repository, https://github.com/vectorsss/gnuplot-style
Project-URL: Issues, https://github.com/vectorsss/gnuplot-style/issues
Keywords: matplotlib,gnuplot,plotting,visualization,style
Classifier: Development Status :: 4 - Beta
Classifier: Intended Audience :: Science/Research
Classifier: License :: OSI Approved :: MIT License
Classifier: Programming Language :: Python :: 3
Classifier: Programming Language :: Python :: 3.8
Classifier: Programming Language :: Python :: 3.9
Classifier: Programming Language :: Python :: 3.10
Classifier: Programming Language :: Python :: 3.11
Classifier: Programming Language :: Python :: 3.12
Classifier: Topic :: Scientific/Engineering :: Visualization
Requires-Python: >=3.8
Requires-Dist: matplotlib>=3.5.0
Requires-Dist: numpy>=1.20.0
Requires-Dist: cycler>=0.10.0
Provides-Extra: dev
Requires-Dist: pytest>=7.0; extra == "dev"
Requires-Dist: pytest-cov>=4.0; extra == "dev"
Requires-Dist: black>=24.0; extra == "dev"
Requires-Dist: isort>=5.12; extra == "dev"
Requires-Dist: flake8>=7.0; extra == "dev"
Requires-Dist: mypy>=1.0; extra == "dev"
Requires-Dist: pre-commit>=3.0; extra == "dev"
Requires-Dist: pydocstyle>=6.3; extra == "dev"
